l3c/__init__.py
l3c/anymdp/__init__.py
l3c/anymdp/anymdp_env.py
l3c/anymdp/anymdp_solver_opt.py
l3c/anymdp/anymdp_solver_ots.py
l3c/anymdp/anymdp_solver_q.py
l3c/anymdp/solver.py
l3c/anymdp/task_sampler.py
l3c/anymdp/test.py
l3c/anymdp/visualizer.py
l3c/anymdpv2/__init__.py
l3c/anymdpv2/anymdp_env.py
l3c/anymdpv2/task_sampler.py
l3c/anymdpv2/test.py
l3c/anymdpv2/test_ppo.py
l3c/anymdpv2/visualizer.py
l3c/mazeworld/__init__.py
l3c/mazeworld/agents/__init__.py
l3c/mazeworld/agents/agent_base.py
l3c/mazeworld/agents/oracle_agent.py
l3c/mazeworld/agents/smart_slam_agent.py
l3c/mazeworld/demo/__init__.py
l3c/mazeworld/demo/agent_play_demo.py
l3c/mazeworld/demo/keyboard_play_demo.py
l3c/mazeworld/envs/__init__.py
l3c/mazeworld/envs/dynamics.py
l3c/mazeworld/envs/grid_ops.py
l3c/mazeworld/envs/maze_base.py
l3c/mazeworld/envs/maze_continuous_3d.py
l3c/mazeworld/envs/maze_env.py
l3c/mazeworld/envs/ray_caster_utils.py
l3c/mazeworld/envs/task_sampler.py
l3c/mazeworld/envs/utils.py
l3c/mazeworld/envs/img/ceiling_asphalt_03_diff_1k.jpg
l3c/mazeworld/envs/img/ceiling_concrete_floor_01_diff_1k.jpg
l3c/mazeworld/envs/img/ceiling_concrete_floor_01_rough_1k.jpg
l3c/mazeworld/envs/img/ceiling_concrete_floor_02_diff_1k.jpg
l3c/mazeworld/envs/img/ceiling_concrete_floor_02_rough_1k.jpg
l3c/mazeworld/envs/img/ceiling_concrete_floor_worn_001_diff_1k.jpg
l3c/mazeworld/envs/img/ceiling_concrete_floor_worn_001_rough_1k.jpg
l3c/mazeworld/envs/img/ceiling_factory_wall_diff_1k.jpg
l3c/mazeworld/envs/img/ceiling_factory_wall_rough_1k.jpg
l3c/mazeworld/envs/img/ceiling_grey_plaster_02_diff_1k.jpg
l3c/mazeworld/envs/img/ceiling_grey_plaster_02_rough_1k.jpg
l3c/mazeworld/envs/img/ceiling_grey_plaster_03_diff_1k.jpg
l3c/mazeworld/envs/img/ceiling_grey_plaster_03_rough_1k.jpg
l3c/mazeworld/envs/img/ceiling_grey_plaster_diff_1k.jpg
l3c/mazeworld/envs/img/ceiling_grey_plaster_rough_1k.jpg
l3c/mazeworld/envs/img/ceiling_metal_plate_02_diff_1k.jpg
l3c-0.2.2.0.dist-info/LICENSE
l3c-0.2.2.0.dist-info/METADATA
l3c-0.2.2.0.dist-info/WHEEL
l3c-0.2.2.0.dist-info/top_level.txt
l3c-0.2.2.0.dist-info/RECORD
