Metadata-Version: 2.1
Name: l3c
Version: 0.2.2.0
Summary: Benchmarks for Lifelong In-Context Learning
Home-page: https://github.com/FutureAGI/L3C
Author: WorldEditors
Author-email: 
License: Apache
Requires-Python: >=3.8
License-File: LICENSE
Requires-Dist: gym >=0.18.0
Requires-Dist: numpy >=1.24.4
Requires-Dist: Pillow >=6.2.2
Requires-Dist: six >=1.12.0
Requires-Dist: pygame >=2.6.0
Requires-Dist: numba >=0.58.1
